vocochat/__init__.py
vocochat/vocochat.py
vocochat-0.1.2.dist-info/LICENSE
vocochat-0.1.2.dist-info/METADATA
vocochat-0.1.2.dist-info/WHEEL
vocochat-0.1.2.dist-info/entry_points.txt
vocochat-0.1.2.dist-info/top_level.txt
vocochat-0.1.2.dist-info/RECORD
